[
     {
          "Вакансия": "Наставник курсов по Python разработке",
          "Компания": "Skyeng",
          "Город": "Москва",
          "ссылка": "https://spb.hh.ru/vacancy/76767074?from=vacancy_search_list&query=python+django+flask",
          "заработная плата": "60 000 – 100 000 руб."
     },
     {
          "Вакансия": "Программист Python (Django)",
          "Компания": "Enjoypro",
          "Город": "Санкт-Петербург",
          "ссылка": "https://spb.hh.ru/vacancy/78665689?from=vacancy_search_list&query=python+django+flask",
          "заработная плата": "160 000 – 180 000 руб."
     },
     {
          "Вакансия": "Middle разработчик Python / Django",
          "Компания": "ООО РА Дельта",
          "Город": "Москва",
          "ссылка": "https://spb.hh.ru/vacancy/78818283?from=vacancy_search_list&query=python+django+flask",
          "заработная плата": "60 000 – 140 000 руб."
     },
     {
          "Вакансия": "Программист Python",
          "Компания": "РусЭкспресс",
          "Город": "Москва",
          "ссылка": "https://spb.hh.ru/vacancy/78926884?from=vacancy_search_list&query=python+django+flask",
          "заработная плата": "70 000 – 100 000 руб."
     },
     {
          "Вакансия": "Middle+ Backend разработчик Python/Django",
          "Компания": "ЧУ ДО Московская школа программистов",
          "Город": "Москва",
          "ссылка": "https://spb.hh.ru/vacancy/78595053?from=vacancy_search_list&query=python+django+flask",
          "заработная плата": "от 220 000 руб."
     },
     {
          "Вакансия": "Программист Python",
          "Компания": "БО-ЭНЕРГО",
          "Город": "Москва",
          "ссылка": "https://spb.hh.ru/vacancy/78853485?from=vacancy_search_list&query=python+django+flask",
          "заработная плата": "130 000 – 130 000 руб."
     },
     {
          "Вакансия": "Senior Python разработчик",
          "Компания": "Carbon Soft",
          "Город": "Москва",
          "ссылка": "https://spb.hh.ru/vacancy/78808681?from=vacancy_search_list&query=python+django+flask",
          "заработная плата": "200 000 – 350 000 руб."
     },
     {
          "Вакансия": "Middle Backend-разработчик (Python, Django)",
          "Компания": "Intelligent Analytics",
          "Город": "Москва",
          "ссылка": "https://spb.hh.ru/vacancy/78916771?from=vacancy_search_list&query=python+django+flask",
          "заработная плата": "до 220 000 руб."
     },
     {
          "Вакансия": "Разработчик Python",
          "Компания": "ООО Универсальная Электронная Платформа",
          "Город": "Москва",
          "ссылка": "https://spb.hh.ru/vacancy/77234310?from=vacancy_search_list&query=python+django+flask",
          "заработная плата": "от 100 000 руб."
     },
     {
          "Вакансия": "Python разработчик (middle+ - senior)",
          "Компания": "КСК-Эйч Ар",
          "Город": "Москва",
          "ссылка": "https://spb.hh.ru/vacancy/78886285?from=vacancy_search_list&query=python+django+flask",
          "заработная плата": "от 250 000 руб."
     },
     {
          "Вакансия": "Python Developer",
          "Компания": "Aston",
          "Город": "Москва",
          "ссылка": "https://spb.hh.ru/vacancy/78820362?from=vacancy_search_list&query=python+django+flask",
          "заработная плата": "200 000 – 340 000 руб."
     },
     {
          "Вакансия": "Python developer",
          "Компания": "Ventra IT Solutions",
          "Город": "Москва",
          "ссылка": "https://spb.hh.ru/vacancy/78914776?from=vacancy_search_list&query=python+django+flask",
          "заработная плата": "до 200 000 руб."
     },
     {
          "Вакансия": "Python Developer",
          "Компания": "Aston",
          "Город": "Санкт-Петербург",
          "ссылка": "https://spb.hh.ru/vacancy/78820290?from=vacancy_search_list&query=python+django+flask",
          "заработная плата": "до 340 000 руб."
     }
]